findimagespdf/cli.py
findimagespdf/models.py
findimagespdf/pathclass.py
findimagespdf/pdffile.py
findimagespdf/utils.py
findimagespdf/version.py
findimagespdf-0.1.2.dist-info/LICENSE
findimagespdf-0.1.2.dist-info/METADATA
findimagespdf-0.1.2.dist-info/WHEEL
findimagespdf-0.1.2.dist-info/entry_points.txt
findimagespdf-0.1.2.dist-info/RECORD
