Metadata-Version: 2.3
Name: findimagespdf
Version: 0.1.2
Summary: Search and save images from PDF files.
License: MIT
Keywords: pdf,pdf-parser,image,pillow
Author: kurotom
Author-email: 55354389+kurotom@users.noreply.github.com
Requires-Python: >=3.9,<4.0
Classifier: Operating System :: OS Independent
Classifier: Programming Language :: Python :: 3.9
Classifier: Programming Language :: Python :: 3.10
Classifier: Programming Language :: Python :: 3.11
Classifier: Programming Language :: Python :: 3.12
Requires-Dist: pillow (>=11.0,<12.0)
Requires-Dist: platformdirs (>=4.3.7,<5.0.0)
Project-URL: Bug Tracker, https://github.com/kurotom/findimagespdf/issues
